Metadata-Version: 2.4
Name: test_keydev_reports
Version: 1.0.0
Summary: A Django app to create reports.
Author-email: KeyDev <d.kalybekuulu@keydev.kg>
License: BSD-3-Clause
Keywords: django,reports,excel,docx
Classifier: Environment :: Web Environment
Classifier: Framework :: Django
Classifier: Framework :: Django :: 4
Classifier: Intended Audience :: Developers
Classifier: License :: OSI Approved :: BSD License
Classifier: Operating System :: OS Independent
Classifier: Programming Language :: Python :: 3.8
Classifier: Programming Language :: Python :: 3.9
Classifier: Programming Language :: Python :: 3.10
Classifier: Topic :: Internet :: WWW/HTTP
Classifier: Topic :: Internet :: WWW/HTTP :: Dynamic Content
Requires-Python: >=3.8
Requires-Dist: Django>=4.1.3
Requires-Dist: openpyxl>=3.0.10
Requires-Dist: pydantic>=2.4
Requires-Dist: xlsxwriter>=3.1.9
Requires-Dist: python-docx>=0.8.11
Requires-Dist: python-docx-replace>=0.4.1
Requires-Dist: celery>=5.3
